{"trial_id": "39", "hyperparameters": {"space": [{"class_name": "Int", "config": {"name": "units", "default": null, "conditions": [], "min_value": 8, "max_value": 8, "step": 1, "sampling": null}}, {"class_name": "Float", "config": {"name": "lasso_lambda", "default": 0.00036590460910260436, "conditions": [], "min_value": 0.00036590460910260436, "max_value": 0.0005488569136539066, "step": null, "sampling": "linear"}}, {"class_name": "Float", "config": {"name": "learning_rate", "default": 0.04564104007511917, "conditions": [], "min_value": 0.04564104007511917, "max_value": 0.06846156011267876, "step": null, "sampling": "linear"}}, {"class_name": "Float", "config": {"name": "momentum", "default": 0.5575398027903541, "conditions": [], "min_value": 0.5575398027903541, "max_value": 0.8363097041855312, "step": null, "sampling": "linear"}}], "values": {"units": 8, "lasso_lambda": 0.0004156678153247729, "learning_rate": 0.052064640142001996, "momentum": 0.803765738341361}}, "metrics": {"metrics": {"loss": {"direction": "min", "observations": [{"value": [0.0065774138395984965], "step": 116}]}, "euclidean_distance": {"direction": "min", "observations": [{"value": [0.08581979076067607], "step": 116}]}, "val_loss": {"direction": "min", "observations": [{"value": [0.006683111889287829], "step": 116}]}, "val_euclidean_distance": {"direction": "min", "observations": [{"value": [0.08615132421255112], "step": 116}]}}}, "score": 0.08615132421255112, "best_step": 116, "status": "COMPLETED"}