{"trial_id": "40", "hyperparameters": {"space": [{"class_name": "Int", "config": {"name": "units", "default": null, "conditions": [], "min_value": 5, "max_value": 5, "step": 1, "sampling": null}}, {"class_name": "Float", "config": {"name": "ridge_lambda", "default": 0.0029334360534435003, "conditions": [], "min_value": 0.0029334360534435003, "max_value": 0.00440015408016525, "step": null, "sampling": "linear"}}, {"class_name": "Float", "config": {"name": "learning_rate", "default": 0.1885683605474522, "conditions": [], "min_value": 0.1885683605474522, "max_value": 0.28285254082117833, "step": null, "sampling": "linear"}}, {"class_name": "Float", "config": {"name": "momentum", "default": 0.3941443605050978, "conditions": [], "min_value": 0.3941443605050978, "max_value": 0.5912165407576467, "step": null, "sampling": "linear"}}], "values": {"units": 5, "ridge_lambda": 0.004315738421644621, "learning_rate": 0.2678947980909998, "momentum": 0.40077580961384257}}, "metrics": {"metrics": {"loss": {"direction": "min", "observations": [{"value": [0.013899043357620636], "step": 26}]}, "mean_absolute_error": {"direction": "min", "observations": [{"value": [0.07191788032650948], "step": 26}]}, "val_loss": {"direction": "min", "observations": [{"value": [0.013459446839988232], "step": 26}]}, "val_mean_absolute_error": {"direction": "min", "observations": [{"value": [0.06990772175292174], "step": 26}]}}}, "score": 0.06990772175292174, "best_step": 26, "status": "COMPLETED"}